{
    "Delay": 5,
    "OrganizationUrl": "https://dev.azure.com/[OrganizationUrl]/",
    "PersonalAccessToken": "PersonalAccessToken",
    "ProjectName": "ProjectName",
    "Queries": [
        {
            "Filters": [
                "[System.WorkItemType] = 'Bug'",
                "[System.TeamProject] = 'ProjectName'",
                "[System.State] <> 'Closed'"
            ],
            "Name": "Open Bugs",
            "Running": true,
            "Type": 0
        },
        {
            "Name": "PRs",
            "RepositoryName": "RepositoryName",
            "Running": true,
            "Type": 1
        }
    ]
}
